fastapi_keycloak_extended/__init__.py
fastapi_keycloak_extended/api.py
fastapi_keycloak_extended/exceptions.py
fastapi_keycloak_extended/model.py
fastapi_keycloak_extended/requirements.txt
tests/__init__.py
tests/app.py
tests/conftest.py
tests/test_functional.py
tests/test_integration.py
fastapi_keycloak_extended-1.0.10.1.dist-info/LICENSE
fastapi_keycloak_extended-1.0.10.1.dist-info/METADATA
fastapi_keycloak_extended-1.0.10.1.dist-info/WHEEL
fastapi_keycloak_extended-1.0.10.1.dist-info/top_level.txt
fastapi_keycloak_extended-1.0.10.1.dist-info/RECORD
