Metadata-Version: 2.1
Name: fastapi-keycloak-extended
Version: 1.0.10.1
Summary: FastAPI Keycloak Extended
Home-page: https://github.com/cedvict/fastapi-keycloak-extended
Author: Cedvict Loknov
Author-email: Cedvict Loknov <cedvict@gmail.com>
Maintainer-email: Cedvict Loknov <cedvict@gmail.com>
Project-URL: Documentation, https://fastapi-keycloak.code-specialist.com/
Keywords: Keycloak,FastAPI,Authentication,Authorization
Classifier: Development Status :: 3 - Alpha
Classifier: Intended Audience :: Developers
Classifier: Topic :: Internet :: WWW/HTTP :: Session
Classifier: Topic :: Internet :: WWW/HTTP :: WSGI
Classifier: Topic :: Software Development :: Libraries :: Application Frameworks
Classifier: Topic :: Software Development :: Libraries :: Python Modules
Classifier: Framework :: FastAPI
Classifier: License :: OSI Approved :: Apache Software License
Classifier: Programming Language :: Python :: 3.8
Requires-Python: >=3.10
License-File: LICENSE
Requires-Dist: fastapi-keycloak >=1.0.10
